LICENSE
MANIFEST.in
README.md
setup.py
magnebot/__init__.py
magnebot/action_status.py
magnebot/arm.py
magnebot/arm_joint.py
magnebot/collision_detection.py
magnebot/constants.py
magnebot/image_frequency.py
magnebot/magnebot.py
magnebot/magnebot_controller.py
magnebot/magnebot_dynamic.py
magnebot/magnebot_static.py
magnebot/paths.py
magnebot/turn_constants.py
magnebot/util.py
magnebot/wheel.py
magnebot.egg-info/PKG-INFO
magnebot.egg-info/SOURCES.txt
magnebot.egg-info/dependency_links.txt
magnebot.egg-info/requires.txt
magnebot.egg-info/top_level.txt
magnebot/__pycache__/__init__.cpython-311.pyc
magnebot/__pycache__/__init__.cpython-37.pyc
magnebot/__pycache__/action_status.cpython-311.pyc
magnebot/__pycache__/action_status.cpython-37.pyc
magnebot/__pycache__/add_on.cpython-37.pyc
magnebot/__pycache__/arm.cpython-311.pyc
magnebot/__pycache__/arm.cpython-37.pyc
magnebot/__pycache__/arm_joint.cpython-311.pyc
magnebot/__pycache__/arm_joint.cpython-37.pyc
magnebot/__pycache__/collision_action.cpython-37.pyc
magnebot/__pycache__/collision_detection.cpython-311.pyc
magnebot/__pycache__/collision_detection.cpython-37.pyc
magnebot/__pycache__/collisions.cpython-37.pyc
magnebot/__pycache__/constants.cpython-311.pyc
magnebot/__pycache__/constants.cpython-37.pyc
magnebot/__pycache__/controller.cpython-37.pyc
magnebot/__pycache__/drive.cpython-37.pyc
magnebot/__pycache__/image_frequency.cpython-311.pyc
magnebot/__pycache__/image_frequency.cpython-37.pyc
magnebot/__pycache__/joint_static.cpython-37.pyc
magnebot/__pycache__/joint_type.cpython-37.pyc
magnebot/__pycache__/magnebot.cpython-311.pyc
magnebot/__pycache__/magnebot.cpython-37.pyc
magnebot/__pycache__/magnebot_controller.cpython-311.pyc
magnebot/__pycache__/magnebot_controller.cpython-37.pyc
magnebot/__pycache__/magnebot_dynamic.cpython-311.pyc
magnebot/__pycache__/magnebot_dynamic.cpython-37.pyc
magnebot/__pycache__/magnebot_static.cpython-311.pyc
magnebot/__pycache__/magnebot_static.cpython-37.pyc
magnebot/__pycache__/object_static.cpython-37.pyc
magnebot/__pycache__/paths.cpython-311.pyc
magnebot/__pycache__/paths.cpython-37.pyc
magnebot/__pycache__/robot.cpython-37.pyc
