Metadata-Version: 2.1
Name: magnebot
Version: 2.2.10
Summary: High-level API for the Magnebot in TDW.
Home-page: https://github.com/alters-mit/magnebot
Author: Esther Alter
Author-email: alters@mit.edu
License: MIT
Keywords: unity simulation tdw robotics
Classifier: Development Status :: 5 - Production/Stable
Classifier: Intended Audience :: Developers
Classifier: Topic :: Software Development
Classifier: License :: OSI Approved :: MIT License
Classifier: Programming Language :: Python :: 3.6
Classifier: Programming Language :: Python :: 3.7
Classifier: Programming Language :: Python :: 3.8
Classifier: Programming Language :: Python :: 3.9
Classifier: Programming Language :: Python :: 3.10
Classifier: Programming Language :: Python :: 3.11
License-File: LICENSE
